CHANGES.txt
LICENSE.txt
MANIFEST.in
README.rst
setup.py
doc/conf.py
doc/index.rst
pyutf8/__init__.py
pyutf8/_speedups.c
pyutf8/ref.py
pyutf8.egg-info/PKG-INFO
pyutf8.egg-info/SOURCES.txt
pyutf8.egg-info/dependency_links.txt
pyutf8.egg-info/top_level.txt
pyutf8.egg-info/zip-safe
pyutf8/tests/__init__.py
pyutf8/tests/test_ref.py
pyutf8/tests/test_valid_utf8_bytes.py