Metadata-Version: 1.0
Name: pyutf8
Version: 0.1.1
Summary: Extension for dealing with valid and invalid UTF-8 strings
Home-page: http://github.com/etrepum/pyutf8
Author: Bob Ippolito
Author-email: bob@redivi.com
License: MIT License
Platform: any
Classifier: Intended Audience :: Developers
Classifier: License :: OSI Approved :: MIT License
Classifier: Programming Language :: Python
Classifier: Topic :: Software Development :: Libraries :: Python Modules
